simpleicons/all.py
simpleicons/icon.py
simpleicons/icons.py
simpleicons/image.py
simpleicons-7.20.0.dist-info/LICENSE
simpleicons-7.20.0.dist-info/WHEEL
simpleicons-7.20.0.dist-info/METADATA
simpleicons-7.20.0.dist-info/RECORD
