Metadata-Version: 2.1
Name: simpleicons
Version: 7.20.0
Summary: Use a wide-range of icons derived from the simple-icons/simple-icons repo in python.
Home-page: https://github.com/sachinraja/simple-icons-py
License: MIT
Author: Sachin Raja
Author-email: sachinraja2349@gmail.com
Requires-Python: >=3.8,<4.0
Classifier: License :: OSI Approved :: MIT License
Classifier: Programming Language :: Python :: 3
Classifier: Programming Language :: Python :: 3.8
Classifier: Programming Language :: Python :: 3.9
Classifier: Programming Language :: Python :: 3.10
Classifier: Programming Language :: Python :: 3.11
Provides-Extra: auto-update
Provides-Extra: imaging
Requires-Dist: GitPython (>=3.1.24,<4.0.0); extra == "auto-update"
Requires-Dist: Pillow (>=9.2.0,<10.0.0); extra == "imaging"
Requires-Dist: reportlab (>=3.6.3,<4.0.0); extra == "imaging"
Requires-Dist: requests (>=2.26.0,<3.0.0); extra == "auto-update"
Requires-Dist: semantic-version (>=2.8.5,<3.0.0); extra == "auto-update"
Requires-Dist: svglib (>=1.1.0,<2.0.0); extra == "imaging"
Project-URL: Repository, https://github.com/sachinraja/simple-icons-py
